HADeploy-0.6.1.data/scripts/hadeploy
HADeploy-0.6.1.dist-info/METADATA
HADeploy-0.6.1.dist-info/RECORD
HADeploy-0.6.1.dist-info/WHEEL
HADeploy-0.6.1.dist-info/entry_points.txt
HADeploy-0.6.1.dist-info/top_level.txt
hadeploy/__init__.py
hadeploy/core/__init__.py
hadeploy/core/const.py
hadeploy/core/context.py
hadeploy/core/dump.py
hadeploy/core/main.py
hadeploy/core/misc.py
hadeploy/core/parser.py
hadeploy/core/plugin.py
hadeploy/core/schema.py
hadeploy/core/templator.py
hadeploy/core/test.py
hadeploy/core/conf/logging.yml
hadeploy/core/master/code.py
hadeploy/core/master/schema.yml
hadeploy/core/templates/ansible.cfg.jj2
hadeploy/core/templates/group_vars_all.jj2
hadeploy/core/templates/inventory.jj2
hadeploy/plugins/__init__.py
hadeploy/plugins/ansible/code.py
hadeploy/plugins/ansible/schema.yml
hadeploy/plugins/ansible_inventories/code.py
hadeploy/plugins/ansible_inventories/schema.yml
hadeploy/plugins/elastic/code.py
hadeploy/plugins/elastic/deploy.yml.jj2
hadeploy/plugins/elastic/remove.yml.jj2
hadeploy/plugins/elastic/schema.yml
hadeploy/plugins/elastic/roles/elastic_modules/README.md
hadeploy/plugins/elastic/roles/elastic_modules/docs/elasticsearch_index.txt
hadeploy/plugins/elastic/roles/elastic_modules/docs/elasticsearch_template.txt
hadeploy/plugins/elastic/roles/elastic_modules/docs/generate.sh
hadeploy/plugins/elastic/roles/elastic_modules/library/elasticsearch_index.py
hadeploy/plugins/elastic/roles/elastic_modules/library/elasticsearch_template.py
hadeploy/plugins/elastic/roles/elastic_modules/meta/main.yml
hadeploy/plugins/elastic/roles/elastic_modules/tasks/main.yml
hadeploy/plugins/files/__init__.py
hadeploy/plugins/files/code.py
hadeploy/plugins/files/deploy.yml.jj2
hadeploy/plugins/files/remove.yml.jj2
hadeploy/plugins/files/schema.yml
hadeploy/plugins/files/roles/lxml/tasks/main.yml
hadeploy/plugins/hbase/code.py
hadeploy/plugins/hbase/deploy.yml.jj2
hadeploy/plugins/hbase/install_hbase_relay.yml.jj2
hadeploy/plugins/hbase/remove.yml.jj2
hadeploy/plugins/hbase/schema.yml
hadeploy/plugins/hbase/helpers/setup.sh
hadeploy/plugins/hbase/helpers/hbload/hbload_uber-0.2.0.jar
