Metadata-Version: 2.1
Name: HADeploy
Version: 0.6.1
Summary: An Hadoop Application deployment tool
Home-page: https://github.com/BROADSoftware/hadeploy
Author: BROADSoftware
Author-email: info@hadeploy.com
License: GPLv3
Keywords: hadoop deployement bigdata big-data hdfs hbase hive kafka ranger
Platform: UNKNOWN
Classifier: Development Status :: 4 - Beta
Classifier: Environment :: Console
Classifier: Intended Audience :: Developers
Classifier: Intended Audience :: Information Technology
Classifier: Intended Audience :: System Administrators
Classifier: License :: OSI Approved :: GNU General Public License v3 or later (GPLv3+)
Classifier: Natural Language :: English
Classifier: Operating System :: POSIX
Classifier: Programming Language :: Python :: 2.7
Classifier: Topic :: System :: Installation/Setup
Classifier: Topic :: System :: Systems Administration
Classifier: Topic :: System :: Software Distribution
Classifier: Topic :: Utilities
Requires-Dist: ansible (>=2.3.0.0)
Requires-Dist: pykwalify (>=1.6.0)
